midas/modules/goa/__init__.py
midas/modules/goa/meta.py
midas/modules/goa/module.py
midas/modules/goa/simulator.py
midas/modules/goa/model/__init__.py
midas/modules/goa/model/coordinator.py
midas/modules/goa/model/grid_analyzer.py
midas/modules/goa/model/grid_forecaster.py
midas/modules/goa/model/grid_observer.py
midas/modules/goa/model/load_estimator.py
midas/modules/goa/model/messenger.py
midas_goa-1.0.0.dist-info/LICENSE
midas_goa-1.0.0.dist-info/METADATA
midas_goa-1.0.0.dist-info/WHEEL
midas_goa-1.0.0.dist-info/top_level.txt
midas_goa-1.0.0.dist-info/RECORD
